inventory_guard/__init__.py
inventory_guard/compare.py
inventory_guard/config.py
inventory_guard/main.py
inventory_guard/output.py
inventory_guard-0.3.0.dist-info/WHEEL
inventory_guard-0.3.0.dist-info/entry_points.txt
inventory_guard-0.3.0.dist-info/METADATA
inventory_guard-0.3.0.dist-info/RECORD
