Metadata-Version: 2.3
Name: inventory-guard
Version: 0.3.0
Summary: Semantic change guard for Ansible inventories - detect unexpected infrastructure changes
Keywords: ansible,inventory,guard,ci-cd,testing,devops
Author: Maarten
Author-email: Maarten <ikmaarten@gmail.com>
License: MIT License
Classifier: Development Status :: 4 - Beta
Classifier: Intended Audience :: System Administrators
Classifier: Intended Audience :: Developers
Classifier: License :: OSI Approved :: MIT License
Classifier: Programming Language :: Python :: 3
Classifier: Programming Language :: Python :: 3.11
Classifier: Programming Language :: Python :: 3.12
Classifier: Programming Language :: Python :: 3.13
Classifier: Topic :: System :: Systems Administration
Classifier: Topic :: Software Development :: Testing
Classifier: Topic :: Utilities
Requires-Dist: ruamel-yaml>=0.18,<0.19
Requires-Python: >=3.11
Project-URL: Homepage, https://github.com/maartenq/inventory-guard
Project-URL: Issues, https://github.com/maartenq/inventory-guard/issues
Project-URL: Repository, https://github.com/maartenq/inventory-guard
